MANIFEST.in
README.md
setup.cfg
setup.py
tap_woocommerce/__init__.py
tap_woocommerce.egg-info/PKG-INFO
tap_woocommerce.egg-info/SOURCES.txt
tap_woocommerce.egg-info/dependency_links.txt
tap_woocommerce.egg-info/entry_points.txt
tap_woocommerce.egg-info/requires.txt
tap_woocommerce.egg-info/top_level.txt
tap_woocommerce/schemas/orders.json